test0519.v
module PRNG(clk,set_syn);
input clk;
input set_syn;
output [3:1] Q;
reg [3:1] Q;

initial
begin
    Q[3:1]=3'b001;
end

always@(posedge clk)
begin
    if(set_syn)
        Q[3:1]= 3'b110;
    else
    begin
        Q[3] <= Q[2];
        Q[2] <= Q[1];
        Q[1] <= Q[3]^Q[1];
    end
end
endmodule

test0519_tb.v
module BCDtoSEVEN_tb();
reg clk_tb,set_tb;
PRNG PRNG_1(.clk(clk_tb), .set_syn(set_tb));

initial
begin
    clk_tb=1'b1;
    set_tb=1'b0;
end

always
begin
    #10 clk_tb = ~clk_tb;
end

initial
begin
    #80 set_tb=1'b1;
    #10 set_tb=1'b0;
end

initial
begin
    #400 $finish;
end

initial
begin
    $dumpfile("test0519.vcd");
    $dumpvars(0,PRNG_1);
end
endmodule

test0519.vcd
$date
	Thu May 19 14:34:55 2022
$end
$version
	Icarus Verilog
$end
$timescale
	1s
$end
$scope module BCDtoSEVEN_tb $end
$scope module PRNG_1 $end
$var wire 1 ! clk $end
$var wire 1 " set_syn $end
$var reg 3 # Q [3:1] $end
$upscope $end
$upscope $end
$enddefinitions $end
#0
$dumpvars
b11 #
0"
1!
$end
#10
0!
#20
b111 #
1!
#30
0!
#40
b110 #
1!
#50
0!
#60
b101 #
1!
#70
0!
#80
b110 #
1!
1"
#90
0!
0"
#100
b101 #
1!
#110
0!
#120
b10 #
1!
#130
0!
#140
b100 #
1!
#150
0!
#160
b1 #
1!
#170
0!
#180
b11 #
1!
#190
0!
#200
b111 #
1!
#210
0!
#220
b110 #
1!
#230
0!
#240
b101 #
1!
#250
0!
#260
b10 #
1!
#270
0!
#280
b100 #
1!
#290
0!
#300
b1 #
1!
#310
0!
#320
b11 #
1!
#330
0!
#340
b111 #
1!
#350
0!
#360
b110 #
1!
#370
0!
#380
b101 #
1!
#390
0!
#400
b10 #
1!
